Metadata-Version: 1.1
Name: pymysqlbatchimport
Version: 0.4.1a0
Summary: A python wrapper of MySql import tools
Home-page: https://github.com/GoPlan/pymysqlbatchimport.git
Author: Duc-Anh Le
Author-email: ducanh.le@cdelta.xyz
License: UNKNOWN
Platform: UNKNOWN
Classifier: Programming Language :: Python :: 3
Classifier: License :: OSI Approved :: GNU Lesser General Public License v3 (LGPLv3)
